MANIFEST.in
setup.cfg
setup.py
astra/CFloat32CustomPython.h
astra/PyAlgorithmFactory.pxd
astra/PyAlgorithmManager.pxd
astra/PyData2DManager.pxd
astra/PyData3DManager.pxd
astra/PyIncludes.pxd
astra/PyIndexManager.pxd
astra/PyMatrixManager.pxd
astra/PyProjector2DFactory.pxd
astra/PyProjector2DManager.pxd
astra/PyProjector3DFactory.pxd
astra/PyProjector3DManager.pxd
astra/PyXMLDocument.pxd
astra/__init__.py
astra/algorithm.py
astra/algorithm_c.pyx
astra/astra.py
astra/astra_c.pyx
astra/creators.py
astra/data2d.py
astra/data2d_c.pyx
astra/data3d.py
astra/data3d_c.pyx
astra/experimental.pyx
astra/extrautils.pyx
astra/functions.py
astra/log.py
astra/log_c.pyx
astra/matlab.py
astra/matrix.py
astra/matrix_c.pyx
astra/optomo.py
astra/plugin.py
astra/plugin_c.pyx
astra/projector.py
astra/projector3d.py
astra/projector3d_c.pyx
astra/projector_c.pyx
astra/pythonutils.py
astra/utils.pxd
astra/utils.pyx
astra-toolbox/.gitignore
astra-toolbox/.travis.yml
astra-toolbox/COPYING
astra-toolbox/NEWS.txt
astra-toolbox/README.md
astra-toolbox/README.txt
astra-toolbox/astra_vc09.sln
astra-toolbox/astra_vc09.vcproj
astra-toolbox/astra_vc11.sln
astra-toolbox/astra_vc11.vcxproj
astra-toolbox/astra_vc11.vcxproj.filters
astra-toolbox/build/Cuda.rules
astra-toolbox/build/linux/Makefile.in
astra-toolbox/build/linux/README.txt
astra-toolbox/build/linux/acinclude.m4
astra-toolbox/build/linux/autogen.sh
astra-toolbox/build/linux/config.guess.dist
astra-toolbox/build/linux/config.sub.dist
astra-toolbox/build/linux/configure.ac
astra-toolbox/build/linux/install-sh.dist
astra-toolbox/build/msvc/gen.py
astra-toolbox/cuda/2d/algo.cu
astra-toolbox/cuda/2d/algo.h
astra-toolbox/cuda/2d/arith.cu
astra-toolbox/cuda/2d/arith.h
astra-toolbox/cuda/2d/astra.cu
astra-toolbox/cuda/2d/astra.h
astra-toolbox/cuda/2d/cgls.cu
astra-toolbox/cuda/2d/cgls.h
astra-toolbox/cuda/2d/darthelper.cu
astra-toolbox/cuda/2d/darthelper.h
astra-toolbox/cuda/2d/dims.h
astra-toolbox/cuda/2d/em.cu
astra-toolbox/cuda/2d/em.h
astratomo.egg-info/PKG-INFO
astratomo.egg-info/SOURCES.txt
astratomo.egg-info/dependency_links.txt
astratomo.egg-info/top_level.txt