Metadata-Version: 1.1
Name: astratomo
Version: 1.8b2
Summary: Python interface to the ASTRA Toolbox
Home-page: http://www.github.com/astra-toolbox/astra-toolbox
Author: D.M. Pelt
Author-email: D.M.Pelt@cwi.nl
License: GPLv3
Platform: UNKNOWN
Requires: numpy
Requires: six
Requires: scipy
Requires: cython
